notifex/__init__.py
notifex/main.py
notifex/prompts.py
notifex-2025.12.21125243.dist-info/METADATA
notifex-2025.12.21125243.dist-info/WHEEL
notifex-2025.12.21125243.dist-info/top_level.txt
notifex-2025.12.21125243.dist-info/RECORD
