Metadata-Version: 2.4
Name: notifex
Version: 2025.12.21125243
Summary: A new package that helps developers extract and structure notification content from iOS and Android devices for use with ClaudeCode. The package takes raw notification text as input and returns a stan
Author-email: notifex <hi@eugene.plus>
License: MIT
Project-URL: Homepage, https://github.com/chigwell/notifex
Requires-Python: >=3.9
Requires-Dist: langchain-llm7>=0.0.0
Requires-Dist: llmatch-messages>=0.0.0
Requires-Dist: langchain-core>=0.3.0
